setup.cfg
setup.py
xanter/_init_.py
xanter/проверка_элементов.py
xanter/работа_с_файлами.py
xanter/терминал.py
xanter.egg-info/PKG-INFO
xanter.egg-info/SOURCES.txt
xanter.egg-info/dependency_links.txt
xanter.egg-info/not-zip-safe
xanter.egg-info/top_level.txt