Metadata-Version: 2.1
Name: xanter
Version: 0.2
Summary: Мои личные инструменты
Author-email: ulianaantonova651@gmail.com
